b2restore.py
b2restore-1.16.data/scripts/b2restore-create-dummy-files
b2restore-1.16.data/scripts/b2restore-create-git
b2restore-1.16.dist-info/METADATA
b2restore-1.16.dist-info/WHEEL
b2restore-1.16.dist-info/entry_points.txt
b2restore-1.16.dist-info/top_level.txt
b2restore-1.16.dist-info/RECORD
