Metadata-Version: 2.4
Name: b2restore
Version: 1.16
Summary: Program to recreate Backblaze B2 file archive at specified date+time
Author-email: Mark Blakeney <mark.blakeney@bullet-systems.net>
License-Expression: GPL-3.0-or-later
Project-URL: Homepage, https://github.com/bulletmark/b2restore
Keywords: backblaze,b2
Classifier: Programming Language :: Python :: 3
Requires-Python: >=3.7
